{"url":"https://api.github.com/repos/52North/WPS/releases/4261613","assets_url":"https://api.github.com/repos/52North/WPS/releases/4261613/assets","upload_url":"https://uploads.github.com/repos/52North/WPS/releases/4261613/assets{?name,label}","html_url":"https://github.com/52North/WPS/releases/tag/WPS-3.6.1","id":4261613,"tag_name":"WPS-3.6.1","target_commitish":"dev","name":"WPS-3.6.1","draft":false,"author":{"login":"bpross-52n","id":3692794,"avatar_url":"https://avatars1.githubusercontent.com/u/3692794?v=4","gravatar_id":"","url":"https://api.github.com/users/bpross-52n","html_url":"https://github.com/bpross-52n","followers_url":"https://api.github.com/users/bpross-52n/followers","following_url":"https://api.github.com/users/bpross-52n/following{/other_user}","gists_url":"https://api.github.com/users/bpross-52n/gists{/gist_id}","starred_url":"https://api.github.com/users/bpross-52n/starred{/owner}{/repo}","subscriptions_url":"https://api.github.com/users/bpross-52n/subscriptions","organizations_url":"https://api.github.com/users/bpross-52n/orgs","repos_url":"https://api.github.com/users/bpross-52n/repos","events_url":"https://api.github.com/users/bpross-52n/events{/privacy}","received_events_url":"https://api.github.com/users/bpross-52n/received_events","type":"User","site_admin":false},"prerelease":false,"created_at":"2016-09-29T09:14:16Z","published_at":"2016-09-29T09:42:25Z","assets":[{"url":"https://api.github.com/repos/52North/WPS/releases/assets/3109779","id":3109779,"name":"52n-wps-webapp-3.6.1.war","label":null,"uploader":{"login":"bpross-52n","id":3692794,"avatar_url":"https://avatars1.githubusercontent.com/u/3692794?v=4","gravatar_id":"","url":"https://api.github.com/users/bpross-52n","html_url":"https://github.com/bpross-52n","followers_url":"https://api.github.com/users/bpross-52n/followers","following_url":"https://api.github.com/users/bpross-52n/following{/other_user}","gists_url":"https://api.github.com/users/bpross-52n/gists{/gist_id}","starred_url":"https://api.github.com/users/bpross-52n/starred{/owner}{/repo}","subscriptions_url":"https://api.github.com/users/bpross-52n/subscriptions","organizations_url":"https://api.github.com/users/bpross-52n/orgs","repos_url":"https://api.github.com/users/bpross-52n/repos","events_url":"https://api.github.com/users/bpross-52n/events{/privacy}","received_events_url":"https://api.github.com/users/bpross-52n/received_events","type":"User","site_admin":false},"content_type":"application/octet-stream","state":"uploaded","size":18969951,"download_count":11,"created_at":"2017-02-02T11:05:06Z","updated_at":"2017-02-02T11:05:27Z","browser_download_url":"https://github.com/52North/WPS/releases/download/WPS-3.6.1/52n-wps-webapp-3.6.1.war"},{"url":"https://api.github.com/repos/52North/WPS/releases/assets/3109780","id":3109780,"name":"wps-3.6.1-geotools-package.zip","label":null,"uploader":{"login":"bpross-52n","id":3692794,"avatar_url":"https://avatars1.githubusercontent.com/u/3692794?v=4","gravatar_id":"","url":"https://api.github.com/users/bpross-52n","html_url":"https://github.com/bpross-52n","followers_url":"https://api.github.com/users/bpross-52n/followers","following_url":"https://api.github.com/users/bpross-52n/following{/other_user}","gists_url":"https://api.github.com/users/bpross-52n/gists{/gist_id}","starred_url":"https://api.github.com/users/bpross-52n/starred{/owner}{/repo}","subscriptions_url":"https://api.github.com/users/bpross-52n/subscriptions","organizations_url":"https://api.github.com/users/bpross-52n/orgs","repos_url":"https://api.github.com/users/bpross-52n/repos","events_url":"https://api.github.com/users/bpross-52n/events{/privacy}","received_events_url":"https://api.github.com/users/bpross-52n/received_events","type":"User","site_admin":false},"content_type":"application/x-zip-compressed","state":"uploaded","size":32980573,"download_count":13,"created_at":"2017-02-02T11:05:34Z","updated_at":"2017-02-02T11:06:08Z","browser_download_url":"https://github.com/52North/WPS/releases/download/WPS-3.6.1/wps-3.6.1-geotools-package.zip"}],"tarball_url":"https://api.github.com/repos/52North/WPS/tarball/WPS-3.6.1","zipball_url":"https://api.github.com/repos/52North/WPS/zipball/WPS-3.6.1","body":" The 52°North Web Processing Service (WPS) enables the deployment of geo-processes on the web in a standardized way.\r\n It features a pluggable architecture for processes and data encodings.\r\n The implementation is based on the OpenGIS specification: 05-007r7.\r\n\r\n## Changes since last release\r\n\r\n### New features ---\r\n- Improved parsing of GML 3.2\r\n\r\n### Changes ---\r\n\r\n### Fixed issues ---\r\n- #228 ExecutionContext.getTempDirectoryPath() misses to put an \"/\" after the java.io.tmpdir property\r\n- #235 Use connect URL in describeProcess\r\n- #236 Replace describeProcess identifier\r\n"}